{"type": "Feature", "id": 12512758, "properties": {"woe:id": 12512758, "woe:parent_id": 1313090, "woe:name": "Bole International Airport", "woe:placetype": 14, "woe:placetype_name": "Airport", "woe:lang": "ENG", "iso:country": "ET", "meta:provider": ["geoplanet:7.3.1", "geoplanet:7.3.2", "geoplanet:7.4.0", "geoplanet:7.4.1", "geoplanet:7.5.1", "geoplanet:7.5.2", "geoplanet:7.6.0", "geoplanet:7.8.1", "geoplanet:7.9.0", "geoplanet:7.10.0", "geoplanet:8.0.0", "woeplanet:8.0.0"], "meta:indexed": "2020-08-20T20:20:43.470783", "woe:alias_ENG_V": ["Bole", "Bole Airport", "Bole International", "ADD", "ADD Airport"], "meta:updated": "2020-08-22T03:00:26.720980", "woe:hierarchy": {"continent": 24865670, "country": 23424808, "town": 0, "planet": 1, "county": 56017370, "suburb": 0, "state": 56013543, "region": 0, "localadmin": 0}, "woe:timezone_id": 28350683, "woe:hash": "scee4fqn7hqt", "woe:centroid": [38.801102, 8.9783], "geom:latitude": 8.9783, "geom:longitude": 38.801102, "geom:hash": "scee4fqn7hqt", "woe:latitude": 8.9783, "geom:centroid": [38.801102, 8.9783], "woe:longitude": 38.801102, "woe:repo": "woeplanet-airport-et"}, "geometry": {"coordinates": [38.801102, 8.9783], "type": "Point"}}